whatintime/__init__.py
whatintime-1.1.0.dist-info/METADATA
whatintime-1.1.0.dist-info/WHEEL
whatintime-1.1.0.dist-info/RECORD
