Metadata-Version: 2.1
Name: whatintime
Version: 1.1.0
Summary: 
Author: thearyadev
Author-email: personal@aryankothari.dev
Requires-Python: >=3.8,<4.0
Classifier: Programming Language :: Python :: 3
Classifier: Programming Language :: Python :: 3.8
Classifier: Programming Language :: Python :: 3.9
Classifier: Programming Language :: Python :: 3.10
Classifier: Programming Language :: Python :: 3.11
